[
  {
    "company_name": "Lennar Homes of California",
    "phone": "(949) 789-1600",
    "email": null,
    "official_website": "https://www.lennar.com/",
    "contact_page_url": "https://www.lennar.com/contact/business-inquiry",
    "license_number": "728102",
    "license_status": "CLEAR",
    "city": "IRVINE",
    "county": "Orange",
    "address": "2000 FIVEPOINT INT 3RD FLOOR",
    "cslb_source_url": "https://www.cslb.ca.gov/OnlineServices/CheckLicenseII/LicenseDetail.aspx?LicNum=728102",
    "website_source_url": "https://www.lennar.com/contact/business-inquiry",
    "enrichment_sources": [
      "cslb_license_master",
      "website_scrape",
      "company_web_sources",
      "contact_web_sources"
    ],
    "confidence": 0.92,
    "last_verified": "2026-07-09T06:59:15.598Z",
    "evidence_summary": "CSLB license 728102 lists business phone (949) 789-1600."
  },
  {
    "company_name": "A 1 ELECTRICAL",
    "phone": "(916) 482-3400",
    "email": null,
    "official_website": null,
    "contact_page_url": null,
    "license_number": "909430",
    "license_status": "CLEAR",
    "city": "SACRAMENTO",
    "county": "Sacramento",
    "address": "221 LATHROP WY STE M",
    "cslb_source_url": "https://www.cslb.ca.gov/OnlineServices/CheckLicenseII/LicenseDetail.aspx?LicNum=909430",
    "website_source_url": null,
    "enrichment_sources": [
      "cslb_license_master",
      "company_web_sources",
      "contact_web_sources"
    ],
    "confidence": 0.92,
    "last_verified": "2026-07-09T06:59:15.598Z",
    "evidence_summary": "CSLB license 909430 lists business phone (916) 482-3400."
  },
  {
    "company_name": "ROBERT L SCHEID CONSTRUCTION",
    "phone": "(916) 947-8089",
    "email": null,
    "official_website": null,
    "contact_page_url": null,
    "license_number": "1063457",
    "license_status": "CLEAR",
    "city": "CHICO",
    "county": "Butte",
    "address": "3286 MIDDLETOWN AVENUE",
    "cslb_source_url": "https://www.cslb.ca.gov/OnlineServices/CheckLicenseII/LicenseDetail.aspx?LicNum=1063457",
    "website_source_url": null,
    "enrichment_sources": [
      "cslb_license_master",
      "company_web_sources",
      "contact_web_sources"
    ],
    "confidence": 0.92,
    "last_verified": "2026-07-09T06:59:15.598Z",
    "evidence_summary": "CSLB license 1063457 lists business phone (916) 947-8089."
  },
  {
    "company_name": "FDC NOR-CAL CORP",
    "phone": "(925) 766-5163",
    "email": null,
    "official_website": null,
    "contact_page_url": null,
    "license_number": "1079515",
    "license_status": "CLEAR",
    "city": "SACRAMENTO",
    "county": "Sacramento",
    "address": "555 UNIVERSITY AVE STE 116",
    "cslb_source_url": "https://www.cslb.ca.gov/OnlineServices/CheckLicenseII/LicenseDetail.aspx?LicNum=1079515",
    "website_source_url": null,
    "enrichment_sources": [
      "cslb_license_master",
      "company_web_sources",
      "contact_web_sources"
    ],
    "confidence": 0.92,
    "last_verified": "2026-07-09T06:59:15.598Z",
    "evidence_summary": "CSLB license 1079515 lists business phone (925) 766-5163."
  },
  {
    "company_name": "ADVANCED ROOF DESIGN INC",
    "phone": "(916) 381-2266",
    "email": null,
    "official_website": "https://www.ardroofing.com/",
    "contact_page_url": "https://caanet.org/industry-directory/advanced-roof-design-inc/",
    "license_number": "672328",
    "license_status": "CLEAR",
    "city": "SACRAMENTO",
    "county": "Sacramento",
    "address": "4 WAYNE COURT BUILDING 10",
    "cslb_source_url": "https://www.cslb.ca.gov/OnlineServices/CheckLicenseII/LicenseDetail.aspx?LicNum=672328",
    "website_source_url": "https://caanet.org/industry-directory/advanced-roof-design-inc/",
    "enrichment_sources": [
      "cslb_license_master",
      "website_scrape",
      "company_web_sources",
      "contact_web_sources"
    ],
    "confidence": 0.92,
    "last_verified": "2026-07-09T06:59:15.598Z",
    "evidence_summary": "CSLB license 672328 lists business phone (916) 381-2266."
  },
  {
    "company_name": "ALLTECH GATES AND ENTRY CONTROLS INC",
    "phone": "(916) 599-6629",
    "email": "alltechgates@gmail.com",
    "official_website": "https://www.alltechgates.com/",
    "contact_page_url": null,
    "license_number": "964909",
    "license_status": "CLEAR",
    "city": "SACRAMENTO",
    "county": "Sacramento",
    "address": "5325 ELKHORN BLVD #314",
    "cslb_source_url": "https://www.cslb.ca.gov/OnlineServices/CheckLicenseII/LicenseDetail.aspx?LicNum=964909",
    "website_source_url": "https://www.alltechgates.com/",
    "enrichment_sources": [
      "cslb_license_master",
      "website_scrape",
      "company_web_sources",
      "contact_web_sources"
    ],
    "confidence": 0.92,
    "last_verified": "2026-07-09T06:59:15.598Z",
    "evidence_summary": "CSLB license 964909 lists business phone (916) 599-6629. Source-backed email alltechgates@gmail.com found for ALLTECH GATES AND ENTRY CONTROLS INC."
  },
  {
    "company_name": "KB HOME SACRAMENTO INC",
    "phone": "(310) 231-4000",
    "email": null,
    "official_website": null,
    "contact_page_url": null,
    "license_number": "255425",
    "license_status": "CLEAR",
    "city": "LOS ANGELES",
    "county": "Los Angeles",
    "address": "10990 WILSHIRE BLVD 7TH FLOORATTN: LEGAL DEPARTMENT",
    "cslb_source_url": "https://www.cslb.ca.gov/OnlineServices/CheckLicenseII/LicenseDetail.aspx?LicNum=255425",
    "website_source_url": null,
    "enrichment_sources": [
      "cslb_license_master",
      "company_web_sources",
      "contact_web_sources"
    ],
    "confidence": 0.92,
    "last_verified": "2026-07-09T06:59:15.598Z",
    "evidence_summary": "CSLB license 255425 lists business phone (310) 231-4000."
  },
  {
    "company_name": "3 GENERATIONS IMPROVEMENTS INC",
    "phone": "(916) 932-2315",
    "email": null,
    "official_website": null,
    "contact_page_url": null,
    "license_number": "876464",
    "license_status": "CLEAR",
    "city": "FOLSOM",
    "county": "Sacramento",
    "address": "101 PARKSHORE DR #100",
    "cslb_source_url": "https://www.cslb.ca.gov/OnlineServices/CheckLicenseII/LicenseDetail.aspx?LicNum=876464",
    "website_source_url": null,
    "enrichment_sources": [
      "cslb_license_master",
      "company_web_sources",
      "contact_web_sources"
    ],
    "confidence": 0.92,
    "last_verified": "2026-07-09T06:59:15.598Z",
    "evidence_summary": "CSLB license 876464 lists business phone (916) 932-2315."
  },
  {
    "company_name": "ALL PRO PLUMBING",
    "phone": "(916) 726-1970",
    "email": null,
    "official_website": null,
    "contact_page_url": null,
    "license_number": "668343",
    "license_status": "CLEAR",
    "city": "CITRUS HEIGHTS",
    "county": "Sacramento",
    "address": "7250 AUBURN BLVD",
    "cslb_source_url": "https://www.cslb.ca.gov/OnlineServices/CheckLicenseII/LicenseDetail.aspx?LicNum=668343",
    "website_source_url": null,
    "enrichment_sources": [
      "cslb_license_master",
      "company_web_sources",
      "contact_web_sources"
    ],
    "confidence": 0.92,
    "last_verified": "2026-07-09T06:59:15.598Z",
    "evidence_summary": "CSLB license 668343 lists business phone (916) 726-1970."
  },
  {
    "company_name": "AMERICAN BUILDINGS J&S",
    "phone": "(530) 788-3256",
    "email": null,
    "official_website": null,
    "contact_page_url": null,
    "license_number": "1137229",
    "license_status": "CLEAR",
    "city": "SACRAMENTO",
    "county": "Sacramento",
    "address": "3250 51ST AVENUE",
    "cslb_source_url": "https://www.cslb.ca.gov/OnlineServices/CheckLicenseII/LicenseDetail.aspx?LicNum=1137229",
    "website_source_url": null,
    "enrichment_sources": [
      "cslb_license_master",
      "company_web_sources",
      "contact_web_sources"
    ],
    "confidence": 0.92,
    "last_verified": "2026-07-09T06:59:15.598Z",
    "evidence_summary": "CSLB license 1137229 lists business phone (530) 788-3256."
  },
  {
    "company_name": "ARCO / MURRAY NATIONAL NORCAL LLC",
    "phone": "(650) 288-1305",
    "email": null,
    "official_website": null,
    "contact_page_url": null,
    "license_number": "1070665",
    "license_status": "CLEAR",
    "city": "EMERYVILLE",
    "county": "Alameda",
    "address": "2000 POWELL STREET STE 305",
    "cslb_source_url": "https://www.cslb.ca.gov/OnlineServices/CheckLicenseII/LicenseDetail.aspx?LicNum=1070665",
    "website_source_url": null,
    "enrichment_sources": [
      "cslb_license_master",
      "company_web_sources",
      "contact_web_sources"
    ],
    "confidence": 0.92,
    "last_verified": "2026-07-09T06:59:15.598Z",
    "evidence_summary": "CSLB license 1070665 lists business phone (650) 288-1305."
  },
  {
    "company_name": "AZTEC SOLAR INC",
    "phone": "(916) 853-2700",
    "email": null,
    "official_website": null,
    "contact_page_url": null,
    "license_number": "550110",
    "license_status": "CLEAR",
    "city": "RANCHO CORDOVA",
    "county": "Sacramento",
    "address": "11370 TRADE CENTER DR. STE 3",
    "cslb_source_url": "https://www.cslb.ca.gov/OnlineServices/CheckLicenseII/LicenseDetail.aspx?LicNum=550110",
    "website_source_url": null,
    "enrichment_sources": [
      "cslb_license_master",
      "company_web_sources",
      "contact_web_sources"
    ],
    "confidence": 0.92,
    "last_verified": "2026-07-09T06:59:15.598Z",
    "evidence_summary": "CSLB license 550110 lists business phone (916) 853-2700."
  },
  {
    "company_name": "BRUCE CONSTRUCTION GROUP LLC",
    "phone": "(707) 688-5345",
    "email": null,
    "official_website": null,
    "contact_page_url": null,
    "license_number": "1087444",
    "license_status": "CLEAR",
    "city": "FAIRFIELD",
    "county": "Solano",
    "address": "1250 OLIVER ROAD SUITE 1248",
    "cslb_source_url": "https://www.cslb.ca.gov/OnlineServices/CheckLicenseII/LicenseDetail.aspx?LicNum=1087444",
    "website_source_url": null,
    "enrichment_sources": [
      "cslb_license_master",
      "company_web_sources",
      "contact_web_sources"
    ],
    "confidence": 0.92,
    "last_verified": "2026-07-09T06:59:15.598Z",
    "evidence_summary": "CSLB license 1087444 lists business phone (707) 688-5345."
  },
  {
    "company_name": "CALIFORNIA RENEWABLE ENERGY",
    "phone": "(916) 804-2243",
    "email": null,
    "official_website": null,
    "contact_page_url": null,
    "license_number": "1068801",
    "license_status": "CLEAR",
    "city": "ROSEVILLE",
    "county": "Placer",
    "address": "2024 OPPORTUNITY DR STE 150",
    "cslb_source_url": "https://www.cslb.ca.gov/OnlineServices/CheckLicenseII/LicenseDetail.aspx?LicNum=1068801",
    "website_source_url": null,
    "enrichment_sources": [
      "cslb_license_master",
      "company_web_sources",
      "contact_web_sources"
    ],
    "confidence": 0.92,
    "last_verified": "2026-07-09T06:59:15.598Z",
    "evidence_summary": "CSLB license 1068801 lists business phone (916) 804-2243."
  },
  {
    "company_name": "CITY SIGNS",
    "phone": "(209) 549-2412",
    "email": null,
    "official_website": null,
    "contact_page_url": null,
    "license_number": "769900",
    "license_status": "CLEAR",
    "city": "MODESTO",
    "county": "Stanislaus",
    "address": "1101 DOKER DRIVE SUITE D",
    "cslb_source_url": "https://www.cslb.ca.gov/OnlineServices/CheckLicenseII/LicenseDetail.aspx?LicNum=769900",
    "website_source_url": null,
    "enrichment_sources": [
      "cslb_license_master",
      "company_web_sources",
      "contact_web_sources"
    ],
    "confidence": 0.92,
    "last_verified": "2026-07-09T06:59:15.598Z",
    "evidence_summary": "CSLB license 769900 lists business phone (209) 549-2412."
  },
  {
    "company_name": "DIEHL'S ELECTRIC",
    "phone": "(209) 471-1947",
    "email": null,
    "official_website": null,
    "contact_page_url": null,
    "license_number": "633545",
    "license_status": "CLEAR",
    "city": "LODI",
    "county": "San Joaquin",
    "address": "P O BOX 615",
    "cslb_source_url": "https://www.cslb.ca.gov/OnlineServices/CheckLicenseII/LicenseDetail.aspx?LicNum=633545",
    "website_source_url": null,
    "enrichment_sources": [
      "cslb_license_master",
      "company_web_sources",
      "contact_web_sources"
    ],
    "confidence": 0.92,
    "last_verified": "2026-07-09T06:59:15.598Z",
    "evidence_summary": "CSLB license 633545 lists business phone (209) 471-1947."
  },
  {
    "company_name": "DURAMAX ROOFING INC",
    "phone": "(916) 543-2929",
    "email": "leo@duramaxroofing.net",
    "official_website": "https://duramaxroofing.net/",
    "contact_page_url": "https://duramaxroofing.net/contact",
    "license_number": "866295",
    "license_status": "CLEAR",
    "city": "NEWCASTLE",
    "county": "Placer",
    "address": "340 HIDDEN ACRES LN",
    "cslb_source_url": "https://www.cslb.ca.gov/OnlineServices/CheckLicenseII/LicenseDetail.aspx?LicNum=866295",
    "website_source_url": "https://duramaxroofing.net/contact",
    "enrichment_sources": [
      "cslb_license_master",
      "website_scrape",
      "company_web_sources",
      "contact_web_sources"
    ],
    "confidence": 0.92,
    "last_verified": "2026-07-09T06:59:15.598Z",
    "evidence_summary": "CSLB license 866295 lists business phone (916) 543-2929. Source-backed email leo@duramaxroofing.net found for DURAMAX ROOFING INC."
  },
  {
    "company_name": "DYER CONSTRUCTION INC",
    "phone": "(916) 869-6960",
    "email": null,
    "official_website": null,
    "contact_page_url": null,
    "license_number": "645755",
    "license_status": "CLEAR",
    "city": "SACRAMENTO",
    "county": "Sacramento",
    "address": "P O BOX 661204",
    "cslb_source_url": "https://www.cslb.ca.gov/OnlineServices/CheckLicenseII/LicenseDetail.aspx?LicNum=645755",
    "website_source_url": null,
    "enrichment_sources": [
      "cslb_license_master",
      "company_web_sources",
      "contact_web_sources"
    ],
    "confidence": 0.92,
    "last_verified": "2026-07-09T06:59:15.598Z",
    "evidence_summary": "CSLB license 645755 lists business phone (916) 869-6960."
  },
  {
    "company_name": "ES SOLAR LLC",
    "phone": "(801) 614-0606",
    "email": null,
    "official_website": null,
    "contact_page_url": null,
    "license_number": "1127444",
    "license_status": "CLEAR",
    "city": "LAYTON",
    "county": "",
    "address": "245 E 2150",
    "cslb_source_url": "https://www.cslb.ca.gov/OnlineServices/CheckLicenseII/LicenseDetail.aspx?LicNum=1127444",
    "website_source_url": null,
    "enrichment_sources": [
      "cslb_license_master",
      "company_web_sources",
      "contact_web_sources"
    ],
    "confidence": 0.92,
    "last_verified": "2026-07-09T06:59:15.598Z",
    "evidence_summary": "CSLB license 1127444 lists business phone (801) 614-0606."
  },
  {
    "company_name": "FAMAND INC",
    "phone": "(916) 988-8808",
    "email": null,
    "official_website": null,
    "contact_page_url": null,
    "license_number": null,
    "license_status": null,
    "city": null,
    "county": null,
    "address": null,
    "cslb_source_url": null,
    "website_source_url": null,
    "enrichment_sources": [
      "company_web_sources",
      "contact_web_sources"
    ],
    "confidence": 0.7,
    "last_verified": "2026-07-09T06:59:15.598Z",
    "evidence_summary": "Source-backed phone (916) 988-8808 found for FAMAND INC."
  },
  {
    "company_name": "GROUP ONE BUILDERS INC",
    "phone": "(916) 983-9953",
    "email": null,
    "official_website": null,
    "contact_page_url": null,
    "license_number": "668907",
    "license_status": "CLEAR",
    "city": "FOLSOM",
    "county": "Sacramento",
    "address": "P O BOX 2135",
    "cslb_source_url": "https://www.cslb.ca.gov/OnlineServices/CheckLicenseII/LicenseDetail.aspx?LicNum=668907",
    "website_source_url": null,
    "enrichment_sources": [
      "cslb_license_master",
      "company_web_sources",
      "contact_web_sources"
    ],
    "confidence": 0.92,
    "last_verified": "2026-07-09T06:59:15.598Z",
    "evidence_summary": "CSLB license 668907 lists business phone (916) 983-9953."
  },
  {
    "company_name": "HAVEN ENERGY SERVICES INC",
    "phone": "(504) 452-3127",
    "email": null,
    "official_website": null,
    "contact_page_url": null,
    "license_number": "1104018",
    "license_status": "CLEAR",
    "city": "AUSTIN",
    "county": "",
    "address": "6115 BACK BAY LANE",
    "cslb_source_url": "https://www.cslb.ca.gov/OnlineServices/CheckLicenseII/LicenseDetail.aspx?LicNum=1104018",
    "website_source_url": null,
    "enrichment_sources": [
      "cslb_license_master",
      "company_web_sources",
      "contact_web_sources"
    ],
    "confidence": 0.92,
    "last_verified": "2026-07-09T06:59:15.598Z",
    "evidence_summary": "CSLB license 1104018 lists business phone (504) 452-3127."
  },
  {
    "company_name": "HEAT AND AIR SOLUTIONS INC",
    "phone": "(530) 401-8768",
    "email": null,
    "official_website": null,
    "contact_page_url": null,
    "license_number": "1133607",
    "license_status": "CLEAR",
    "city": "APPLEGATE",
    "county": "Placer",
    "address": "PO BOX 684",
    "cslb_source_url": "https://www.cslb.ca.gov/OnlineServices/CheckLicenseII/LicenseDetail.aspx?LicNum=1133607",
    "website_source_url": null,
    "enrichment_sources": [
      "cslb_license_master",
      "company_web_sources",
      "contact_web_sources"
    ],
    "confidence": 0.92,
    "last_verified": "2026-07-09T06:59:15.598Z",
    "evidence_summary": "CSLB license 1133607 lists business phone (530) 401-8768."
  },
  {
    "company_name": "KENNETH DEVELOPMENT INC",
    "phone": "(916) 939-1615",
    "email": "kennethdevelopment54@gmail.com",
    "official_website": "https://www.kennethdevelopment.com/",
    "contact_page_url": null,
    "license_number": "773369",
    "license_status": "CLEAR",
    "city": "EL DORADO HILLS",
    "county": "El Dorado",
    "address": "P O BOX 4946",
    "cslb_source_url": "https://www.cslb.ca.gov/OnlineServices/CheckLicenseII/LicenseDetail.aspx?LicNum=773369",
    "website_source_url": "https://www.kennethdevelopment.com/",
    "enrichment_sources": [
      "cslb_license_master",
      "website_scrape",
      "company_web_sources",
      "contact_web_sources"
    ],
    "confidence": 0.92,
    "last_verified": "2026-07-09T06:59:15.598Z",
    "evidence_summary": "CSLB license 773369 lists business phone (916) 939-1615. Source-backed email kennethdevelopment54@gmail.com found for KENNETH DEVELOPMENT INC."
  },
  {
    "company_name": "LEGACY DEMOLITION LLC",
    "phone": "(510) 860-1325",
    "email": null,
    "official_website": null,
    "contact_page_url": null,
    "license_number": "1122603",
    "license_status": "CLEAR",
    "city": "NORTH HIGHLANDS",
    "county": "Sacramento",
    "address": "6532 HOLIDAY WAY",
    "cslb_source_url": "https://www.cslb.ca.gov/OnlineServices/CheckLicenseII/LicenseDetail.aspx?LicNum=1122603",
    "website_source_url": null,
    "enrichment_sources": [
      "cslb_license_master",
      "company_web_sources",
      "contact_web_sources"
    ],
    "confidence": 0.92,
    "last_verified": "2026-07-09T06:59:15.598Z",
    "evidence_summary": "CSLB license 1122603 lists business phone (510) 860-1325."
  },
  {
    "company_name": "Lund Construction Co",
    "phone": "(650) 656-7986",
    "email": null,
    "official_website": "https://lundconstruction.com/contact",
    "contact_page_url": "https://lundconstruction.com/contact",
    "license_number": "1086700",
    "license_status": "CLEAR",
    "city": "AUBURN",
    "county": "Placer",
    "address": "1999 VADA RANCH ROAD",
    "cslb_source_url": "https://www.cslb.ca.gov/OnlineServices/CheckLicenseII/LicenseDetail.aspx?LicNum=1086700",
    "website_source_url": "https://lundconstruction.com/contact",
    "enrichment_sources": [
      "cslb_license_master",
      "website_scrape",
      "company_web_sources",
      "contact_web_sources"
    ],
    "confidence": 0.92,
    "last_verified": "2026-07-09T06:59:15.598Z",
    "evidence_summary": "CSLB license 1086700 lists business phone (650) 656-7986."
  },
  {
    "company_name": "NCO DEVELOPMENT",
    "phone": "(530) 606-0257",
    "email": null,
    "official_website": null,
    "contact_page_url": null,
    "license_number": "1085867",
    "license_status": "CLEAR",
    "city": "TRUCKEE",
    "county": "Nevada",
    "address": "11820 COBURN DR",
    "cslb_source_url": "https://www.cslb.ca.gov/OnlineServices/CheckLicenseII/LicenseDetail.aspx?LicNum=1085867",
    "website_source_url": null,
    "enrichment_sources": [
      "cslb_license_master",
      "company_web_sources",
      "contact_web_sources"
    ],
    "confidence": 0.92,
    "last_verified": "2026-07-09T06:59:15.598Z",
    "evidence_summary": "CSLB license 1085867 lists business phone (530) 606-0257."
  },
  {
    "company_name": "NEXT DEMOLITION LLC",
    "phone": "(650) 680-6768",
    "email": null,
    "official_website": null,
    "contact_page_url": null,
    "license_number": "1141839",
    "license_status": "CLEAR",
    "city": "ROSEVILLE",
    "county": "Placer",
    "address": "6008 ORANGE TIP WAY",
    "cslb_source_url": "https://www.cslb.ca.gov/OnlineServices/CheckLicenseII/LicenseDetail.aspx?LicNum=1141839",
    "website_source_url": null,
    "enrichment_sources": [
      "cslb_license_master",
      "company_web_sources",
      "contact_web_sources"
    ],
    "confidence": 0.92,
    "last_verified": "2026-07-09T06:59:15.598Z",
    "evidence_summary": "CSLB license 1141839 lists business phone (650) 680-6768."
  },
  {
    "company_name": "PHILLIP ISAACS' CONSTRUCTION INCORPORATED",
    "phone": "(916) 852-8132",
    "email": null,
    "official_website": null,
    "contact_page_url": null,
    "license_number": "627677",
    "license_status": "CLEAR",
    "city": "ORANGEVALE",
    "county": "Sacramento",
    "address": "9380 ORANGEVALE",
    "cslb_source_url": "https://www.cslb.ca.gov/OnlineServices/CheckLicenseII/LicenseDetail.aspx?LicNum=627677",
    "website_source_url": null,
    "enrichment_sources": [
      "cslb_license_master",
      "company_web_sources",
      "contact_web_sources"
    ],
    "confidence": 0.92,
    "last_verified": "2026-07-09T06:59:15.598Z",
    "evidence_summary": "CSLB license 627677 lists business phone (916) 852-8132."
  },
  {
    "company_name": "PRIME HOME SOLUTIONS INC",
    "phone": "(916) 667-7480",
    "email": "info@primehomesolutions.com",
    "official_website": "https://primehomesolutions.com/",
    "contact_page_url": null,
    "license_number": "1075385",
    "license_status": "CLEAR",
    "city": "ROSEVILLE",
    "county": "Placer",
    "address": "2017 OPPORTUNITY DR SUITE 7",
    "cslb_source_url": "https://www.cslb.ca.gov/OnlineServices/CheckLicenseII/LicenseDetail.aspx?LicNum=1075385",
    "website_source_url": "https://primehomesolutions.com/",
    "enrichment_sources": [
      "cslb_license_master",
      "website_scrape",
      "company_web_sources",
      "contact_web_sources"
    ],
    "confidence": 0.92,
    "last_verified": "2026-07-09T06:59:15.598Z",
    "evidence_summary": "CSLB license 1075385 lists business phone (916) 667-7480. Source-backed email info@primehomesolutions.com found for PRIME HOME SOLUTIONS INC."
  },
  {
    "company_name": "SOLACE ENTERPRISES INC",
    "phone": "(916) 463-0100",
    "email": null,
    "official_website": null,
    "contact_page_url": null,
    "license_number": "913717",
    "license_status": "CLEAR",
    "city": "RANCHO CORDOVA",
    "county": "Sacramento",
    "address": "11092 SUN CENTER DR",
    "cslb_source_url": "https://www.cslb.ca.gov/OnlineServices/CheckLicenseII/LicenseDetail.aspx?LicNum=913717",
    "website_source_url": null,
    "enrichment_sources": [
      "cslb_license_master",
      "company_web_sources",
      "contact_web_sources"
    ],
    "confidence": 0.92,
    "last_verified": "2026-07-09T06:59:15.598Z",
    "evidence_summary": "CSLB license 913717 lists business phone (916) 463-0100."
  },
  {
    "company_name": "SPEED PLUMBING PRO",
    "phone": "(707) 761-2626",
    "email": null,
    "official_website": null,
    "contact_page_url": null,
    "license_number": "1084778",
    "license_status": "CLEAR",
    "city": "SACRAMENTO",
    "county": "Sacramento",
    "address": "7431 POIRIER WAY",
    "cslb_source_url": "https://www.cslb.ca.gov/OnlineServices/CheckLicenseII/LicenseDetail.aspx?LicNum=1084778",
    "website_source_url": null,
    "enrichment_sources": [
      "cslb_license_master",
      "company_web_sources",
      "contact_web_sources"
    ],
    "confidence": 0.92,
    "last_verified": "2026-07-09T06:59:15.598Z",
    "evidence_summary": "CSLB license 1084778 lists business phone (707) 761-2626."
  },
  {
    "company_name": "SUNSOURCE INC",
    "phone": "(888) 672-3297",
    "email": null,
    "official_website": null,
    "contact_page_url": null,
    "license_number": "1117770",
    "license_status": "CLEAR",
    "city": "FOLSOM",
    "county": "Sacramento",
    "address": "1024 IRON POINT RD",
    "cslb_source_url": "https://www.cslb.ca.gov/OnlineServices/CheckLicenseII/LicenseDetail.aspx?LicNum=1117770",
    "website_source_url": null,
    "enrichment_sources": [
      "cslb_license_master",
      "company_web_sources",
      "contact_web_sources"
    ],
    "confidence": 0.92,
    "last_verified": "2026-07-09T06:59:15.598Z",
    "evidence_summary": "CSLB license 1117770 lists business phone (888) 672-3297."
  },
  {
    "company_name": "VEERKAMP DOUG GENERAL ENGINEERING INC",
    "phone": "(530) 676-0825",
    "email": null,
    "official_website": null,
    "contact_page_url": null,
    "license_number": "440233",
    "license_status": "CLEAR",
    "city": "CAMERON PARK",
    "county": "El Dorado",
    "address": "3701 TRADEWAY",
    "cslb_source_url": "https://www.cslb.ca.gov/OnlineServices/CheckLicenseII/LicenseDetail.aspx?LicNum=440233",
    "website_source_url": null,
    "enrichment_sources": [
      "cslb_license_master",
      "company_web_sources",
      "contact_web_sources"
    ],
    "confidence": 0.92,
    "last_verified": "2026-07-09T06:59:15.598Z",
    "evidence_summary": "CSLB license 440233 lists business phone (530) 676-0825."
  },
  {
    "company_name": "WATERS CONSTRUCTION COMPANY LLC",
    "phone": "(916) 594-8912",
    "email": "owner@waterscco.com",
    "official_website": "https://watersconco.com/",
    "contact_page_url": "https://watersconco.com/",
    "license_number": "1129256",
    "license_status": "CLEAR",
    "city": "CARMICHAEL",
    "county": "Sacramento",
    "address": "4340 COLLEGE VIEW WAY",
    "cslb_source_url": "https://www.cslb.ca.gov/OnlineServices/CheckLicenseII/LicenseDetail.aspx?LicNum=1129256",
    "website_source_url": "https://watersconco.com/",
    "enrichment_sources": [
      "cslb_license_master",
      "website_scrape",
      "company_web_sources",
      "contact_web_sources"
    ],
    "confidence": 0.92,
    "last_verified": "2026-07-09T06:59:15.598Z",
    "evidence_summary": "CSLB license 1129256 lists business phone (916) 594-8912. Source-backed email owner@waterscco.com found for WATERS CONSTRUCTION COMPANY LLC."
  },
  {
    "company_name": "WEST COAST FLOORING",
    "phone": "(209) 595-1950",
    "email": null,
    "official_website": null,
    "contact_page_url": null,
    "license_number": "876162",
    "license_status": "CLEAR",
    "city": "MODESTO",
    "county": "Stanislaus",
    "address": "1100 STRATFORD LN",
    "cslb_source_url": "https://www.cslb.ca.gov/OnlineServices/CheckLicenseII/LicenseDetail.aspx?LicNum=876162",
    "website_source_url": null,
    "enrichment_sources": [
      "cslb_license_master",
      "company_web_sources",
      "contact_web_sources"
    ],
    "confidence": 0.92,
    "last_verified": "2026-07-09T06:59:15.598Z",
    "evidence_summary": "CSLB license 876162 lists business phone (209) 595-1950."
  },
  {
    "company_name": "AMERICAN CARPORTS INC",
    "phone": "(866) 730-9865",
    "email": null,
    "official_website": null,
    "contact_page_url": null,
    "license_number": "879371",
    "license_status": "CLEAR",
    "city": "JOSHUA",
    "county": "",
    "address": "PO BOX 38",
    "cslb_source_url": "https://www.cslb.ca.gov/OnlineServices/CheckLicenseII/LicenseDetail.aspx?LicNum=879371",
    "website_source_url": null,
    "enrichment_sources": [
      "cslb_license_master",
      "company_web_sources",
      "contact_web_sources"
    ],
    "confidence": 0.92,
    "last_verified": "2026-07-09T06:59:15.598Z",
    "evidence_summary": "CSLB license 879371 lists business phone (866) 730-9865."
  },
  {
    "company_name": "BURNS CONSTRUCTION",
    "phone": "(916) 768-2645",
    "email": null,
    "official_website": null,
    "contact_page_url": null,
    "license_number": "885789",
    "license_status": "CLEAR",
    "city": "CARMICHAEL",
    "county": "Sacramento",
    "address": "4624 SHAFTESBURY CT",
    "cslb_source_url": "https://www.cslb.ca.gov/OnlineServices/CheckLicenseII/LicenseDetail.aspx?LicNum=885789",
    "website_source_url": null,
    "enrichment_sources": [
      "cslb_license_master",
      "company_web_sources",
      "contact_web_sources"
    ],
    "confidence": 0.92,
    "last_verified": "2026-07-09T06:59:15.598Z",
    "evidence_summary": "CSLB license 885789 lists business phone (916) 768-2645."
  },
  {
    "company_name": "DEOME 2 BUILDERS INC",
    "phone": "(916) 412-2517",
    "email": null,
    "official_website": null,
    "contact_page_url": null,
    "license_number": "873885",
    "license_status": "CLEAR",
    "city": "ANTELOPE",
    "county": "Sacramento",
    "address": "8401 HIDDEN PASS CT",
    "cslb_source_url": "https://www.cslb.ca.gov/OnlineServices/CheckLicenseII/LicenseDetail.aspx?LicNum=873885",
    "website_source_url": null,
    "enrichment_sources": [
      "cslb_license_master",
      "company_web_sources",
      "contact_web_sources"
    ],
    "confidence": 0.92,
    "last_verified": "2026-07-09T06:59:15.598Z",
    "evidence_summary": "CSLB license 873885 lists business phone (916) 412-2517."
  },
  {
    "company_name": "KUSTOM US INC",
    "phone": "(407) 965-1940",
    "email": null,
    "official_website": null,
    "contact_page_url": null,
    "license_number": "988872",
    "license_status": "CLEAR",
    "city": "LONGWOOD",
    "county": "",
    "address": "640 E STATE ROAD 434 STE 1000",
    "cslb_source_url": "https://www.cslb.ca.gov/OnlineServices/CheckLicenseII/LicenseDetail.aspx?LicNum=988872",
    "website_source_url": null,
    "enrichment_sources": [
      "cslb_license_master",
      "company_web_sources",
      "contact_web_sources"
    ],
    "confidence": 0.92,
    "last_verified": "2026-07-09T06:59:15.598Z",
    "evidence_summary": "CSLB license 988872 lists business phone (407) 965-1940."
  },
  {
    "company_name": "O'CONNOR POOL SOLUTIONS INC",
    "phone": "(916) 871-5097",
    "email": null,
    "official_website": null,
    "contact_page_url": null,
    "license_number": "1071914",
    "license_status": "CLEAR",
    "city": "ROSEVILLE",
    "county": "Placer",
    "address": "108 ARTHUR CT",
    "cslb_source_url": "https://www.cslb.ca.gov/OnlineServices/CheckLicenseII/LicenseDetail.aspx?LicNum=1071914",
    "website_source_url": null,
    "enrichment_sources": [
      "cslb_license_master",
      "company_web_sources",
      "contact_web_sources"
    ],
    "confidence": 0.92,
    "last_verified": "2026-07-09T06:59:15.598Z",
    "evidence_summary": "CSLB license 1071914 lists business phone (916) 871-5097."
  }
]
